sentry_tools/__init__.py
sentry_tools/decorators.py
sentry_tools/span.py
sentry_tools-0.0.3.dist-info/LICENSE
sentry_tools-0.0.3.dist-info/METADATA
sentry_tools-0.0.3.dist-info/WHEEL
sentry_tools-0.0.3.dist-info/top_level.txt
sentry_tools-0.0.3.dist-info/RECORD
